inspec.py
inspec_core/__init__.py
inspec_core/audio_utils.py
inspec_core/cli.py
inspec_core/colormaps.py
inspec_core/options.py
inspec_core/test_spectrogram.py
inspec_core/app/__init__.py
inspec_core/app/app.py
inspec_core/app/draw.py
inspec_core/app/events.py
inspec_core/app/key_handlers.py
inspec_core/app/paginate.py
inspec_core/app/test_paginate.py
inspec_core/app/video_example.py
inspec_core/components/__init__.py
inspec_core/components/audio_view.py
inspec_core/components/base_view.py
inspec_core/components/image_view.py
inspec_core/components/live_audio_view.py
inspec_core/components/size.py
inspec_core/components/test_preserve_aspect_ratio.py
inspec_core/components/test_views.py
inspec_core/components/video_view.py
inspec_core/inspec_curses/__init__.py
inspec_core/inspec_curses/color_pair.py
inspec_core/inspec_curses/context.py
inspec_core/inspec_curses/debug.py
inspec_core/inspec_curses/test_color_pair.py
inspec_core/inspec_curses/test_context.py
inspec_core/inspec_curses/utils.py
inspec_core/render/__init__.py
inspec_core/render/chars.py
inspec_core/render/colors.py
inspec_core/render/display.py
inspec_core/render/renderer.py
inspec_core/render/test_render.py
inspec_core/render/types.py
inspec_core/render/x256.py
inspec-0.5.dist-info/LICENSE
inspec-0.5.dist-info/METADATA
inspec-0.5.dist-info/WHEEL
inspec-0.5.dist-info/entry_points.txt
inspec-0.5.dist-info/top_level.txt
inspec-0.5.dist-info/RECORD
