Metadata-Version: 2.1
Name: inspec
Version: 0.5
Summary: Inspect audio and image files from command line
Author-email: Kevin Yu <thekevinyu@gmail.edu>
License: MIT License
Project-URL: Repository, https://github.com/kevinyu/inspec
Keywords: spectrogram,audio,visualization,sound,terminal
Classifier: Development Status :: 4 - Beta
Classifier: Programming Language :: Python :: 3.0
Classifier: Operating System :: OS Independent
Requires-Python: >=3.10
License-File: LICENSE
Requires-Dist: Pillow
Requires-Dist: click
Requires-Dist: numpy
Requires-Dist: opencv-python
Requires-Dist: pydantic
Requires-Dist: sounddevice
Requires-Dist: soundfile
Requires-Dist: typing-extensions
Requires-Dist: wheel
Requires-Dist: windows-curses ; platform_system == "Windows"
Provides-Extra: dev
Requires-Dist: black ; extra == 'dev'
Requires-Dist: build ; extra == 'dev'
Requires-Dist: flake8 ; extra == 'dev'
Requires-Dist: ipdb ; extra == 'dev'
Requires-Dist: isort ; extra == 'dev'
Requires-Dist: pre-commit ; extra == 'dev'
Requires-Dist: pyright ; extra == 'dev'
Requires-Dist: pytest ; extra == 'dev'
Requires-Dist: twine ; extra == 'dev'
